odoo/addons/sequence_custom_data/README.rst
odoo/addons/sequence_custom_data/__init__.py
odoo/addons/sequence_custom_data/__manifest__.py
odoo/addons/sequence_custom_data/i18n/sequence_custom_data.pot
odoo/addons/sequence_custom_data/models/__init__.py
odoo/addons/sequence_custom_data/models/ir_sequence.py
odoo/addons/sequence_custom_data/readme/CONTRIBUTORS.rst
odoo/addons/sequence_custom_data/readme/DESCRIPTION.rst
odoo/addons/sequence_custom_data/readme/USAGE.rst
odoo/addons/sequence_custom_data/static/description/icon.png
odoo/addons/sequence_custom_data/static/description/index.html
odoo/addons/sequence_custom_data/tests/__init__.py
odoo/addons/sequence_custom_data/tests/test_ir_sequence.py
odoo13_addon_sequence_custom_data-13.0.1.0.1.dist-info/METADATA
odoo13_addon_sequence_custom_data-13.0.1.0.1.dist-info/WHEEL
odoo13_addon_sequence_custom_data-13.0.1.0.1.dist-info/top_level.txt
odoo13_addon_sequence_custom_data-13.0.1.0.1.dist-info/RECORD
