Metadata-Version: 2.1
Name: odoo13-addon-sequence-custom-data
Version: 13.0.1.0.1
Summary: Technical addon used to add some custom codes into the sequence (used for prefix/suffix).
Home-page: https://github.com/OCA/server-tools
Author: ACSONE SA/NV,Odoo Community Association (OCA)
Author-email: support@odoo-community.org
License: AGPL-3
Platform: UNKNOWN
Classifier: Programming Language :: Python
Classifier: Framework :: Odoo
Classifier: Framework :: Odoo :: 13.0
Classifier: License :: OSI Approved :: GNU Affero General Public License v3
Requires-Python: >=3.5
Requires-Dist: odoo (<13.1dev,>=13.0a)
